CHANGES.txt
LICENSE
MANIFEST.in
README.rst
requirements.txt
setup.py
isonet/__init__.py
isonet/bibtex.py
isonet/constants.py
isonet/icon.png
isonet/protocols.conf
isonet/utils.py
isonet/protocols/__init__.py
isonet/protocols/protocol_tomo_reconstruction.py
isonet/tests/__init__.py
isonet/tests/test_protocols_isonet.py
scipion_em_isonet.egg-info/PKG-INFO
scipion_em_isonet.egg-info/SOURCES.txt
scipion_em_isonet.egg-info/dependency_links.txt
scipion_em_isonet.egg-info/entry_points.txt
scipion_em_isonet.egg-info/requires.txt
scipion_em_isonet.egg-info/top_level.txt