Metadata-Version: 1.0
Name: scipion-em-isonet
Version: 3.0.1
Summary: Scipion plugin isonet.
Home-page: https://github.com/scipion-em/scipion-em-isonet
Author: Y.C. Fonseca Reyna && J.L. Vilas
Author-email: cfonseca@cnb.csic.es
License: UNKNOWN
Keywords: scipion cryoem imageprocessing scipion-3.0
Platform: UNKNOWN
